{"VERB+NOUN": 835, "NOUN+ADJF": 1014, "ADJF+ADJF": 240, "ADJF+NOUN": 1218, "NOUN+NOUN": 1503, "ADJF+VERB": 302, "VERB+VERB": 276, "VERB+ADJF": 416, "NOUN+GRND": 106, "GRND+NOUN": 98, "NOUN+ADJS": 100, "ADJS+ADVB": 26, "ADVB+NOUN": 257, "NOUN+VERB": 972, "VERB+INFN": 48, "INFN+ADVB": 18, "ADJF+ADVB": 86, "ADVB+ADVB": 75, "NOUN+ADVB": 308, "ADVB+VERB": 208, "VERB+ADVB": 200, "ADVB+ADJF": 114, "NOUN+PRTF": 65, "PRTF+NOUN": 72, "ADJS+NOUN": 104, "VERB+PRTF": 25, "VERB+GRND": 34, "ADJF+ADJS": 25, "ADJF+COMP": 6, "COMP+ADJF": 4, "ADJS+ADJS": 15, "ADJS+VERB": 32, "VERB+ADJS": 48, "ADJS+ADJF": 36, "GRND+ADJF": 43, "VERB+COMP": 6, "COMP+NOUN": 8, "ADJF+GRND": 28, "ADVB+PRED": 5, "PRED+NOUN": 14, "ADJF+PRED": 3, "ADJF+PRTS": 4, "PRTS+ADJF": 11, "ADVB+INFN": 20, "INFN+NOUN": 62, "ADJF+INFN": 13, "INFN+ADJF": 37, "NOUN+INFN": 65, "INFN+PRTF": 2, "NOUN+COMP": 13, "COMP+VERB": 11, "PRTF+ADVB": 8, "ADJS+INFN": 6, "GRND+ADJS": 2, "ADJS+GRND": 3, "GRND+VERB": 36, "ADVB+GRND": 19, "GRND+ADVB": 12, "COMP+ADJS": 2, "ADVB+PRTS": 6, "PRTS+NOUN": 24, "COMP+ADVB": 2, "GRND+INFN": 4, "ADVB+PRTF": 12, "INFN+ADJS": 6, "INFN+VERB": 33, "NOUN+PRTS": 38, "PRTS+ADVB": 10, "PRTF+VERB": 19, "PRTF+ADJF": 16, "INFN+PRED": 1, "ADVB+ADJS": 26, "PRTS+VERB": 7, "PRTF+GRND": 2, "GRND+GRND": 2, "COMP+GRND": 2, "INFN+GRND": 2, "VERB+PRED": 9, "PRED+PRED": 1, "PRED+ADJF": 5, "NOUN+PRED": 10, "PRED+INFN": 4, "ADJF+PRTF": 11, "PRTF+COMP": 1, "COMP+PRED": 1, "PRED+VERB": 5, "VERB+PRTS": 5, "ADVB+COMP": 4, "COMP+COMP": 1, "PRED+ADVB": 1, "ADJS+PRTF": 2, "GRND+PRTF": 1, "PRTS+COMP": 1, "PRTS+PRTS": 1, "COMP+INFN": 1}